MANIFEST.in
console
coreworker
ez_setup.py
ndm
postsetup.py
setup.py
AsynCluster.egg-info/PKG-INFO
AsynCluster.egg-info/SOURCES.txt
AsynCluster.egg-info/dependency_links.txt
AsynCluster.egg-info/requires.txt
AsynCluster.egg-info/top_level.txt
AsynCluster.egg-info/zip-safe
asyncluster/__init__.py
asyncluster/util.py
asyncluster/master/__init__.py
asyncluster/master/control.py
asyncluster/master/database.py
asyncluster/master/jobs.py
asyncluster/master/nodes.py
asyncluster/master/test/__init__.py
asyncluster/master/test/mock.py
asyncluster/master/test/test_control.py
asyncluster/master/test/test_database.py
asyncluster/master/test/test_nodes.py
asyncluster/ndm/__init__.py
asyncluster/ndm/client.py
asyncluster/ndm/gui.py
asyncluster/ndm/node.py
asyncluster/ndm/worker.py
asyncluster/ndm/test/__init__.py
asyncluster/ndm/test/test_client.py
asyncluster/test/__init__.py
doc/AsynCluster_Example.txt
doc/example.py
doc/gevolver/knapsack.py
gevolver/__init__.py
gevolver/grammar.py
gevolver/individual.py
gevolver/pbge/__init__.py
gevolver/test/__init__.py
misc/etc_asyncluster.conf
misc/etc_init.d_asyncluster
misc/usr_lib_asyncluster.tac
