Metadata-Version: 1.0
Name: AsynCluster
Version: 0.3
Summary:  Asynchronous cluster management based on the Twisted framework, with evolutionary computing tools for asynchronous node processing. 
Home-page: http://foss.eepatents.com/AsynCluster/
Author: Edwin A. Suominen
Author-email: ed@eepatents.com
License: GPL
Keywords: Twisted,asynchronous,taskqueue,queue,priority,tasks,jobs,cluster,clustering,parallel,grid,genetic,evolution,evolutionary computing,GE,GA,GP
Platform: OS Independent
Classifier: Development Status :: 4 - Beta
Classifier: Intended Audience :: Developers
Classifier: Intended Audience :: System Administrators
Classifier: License :: OSI Approved :: GNU General Public License (GPL)
Classifier: Operating System :: OS Independent
Classifier: Programming Language :: Python
Classifier: Topic :: Software Development :: Libraries :: Python Modules
Classifier: Topic :: Software Development :: Object Brokering
Classifier: Topic :: System :: Distributed Computing
Classifier: Topic :: Terminals :: Terminal Emulators/X Terminals
Classifier: Topic :: Desktop Environment :: Window Managers
